llm_proxier/__init__.py
llm_proxier/admin_api.py
llm_proxier/config.py
llm_proxier/database.py
llm_proxier/main.py
llm_proxier/proxy.py
llm_proxier/assets/icon.svg
llm_proxier/templates/admin.html
llm_proxier/templates/admin_start.html
llm_proxier-0.3.0.dist-info/METADATA
llm_proxier-0.3.0.dist-info/WHEEL
llm_proxier-0.3.0.dist-info/entry_points.txt
llm_proxier-0.3.0.dist-info/licenses/LICENSE
llm_proxier-0.3.0.dist-info/RECORD
