Metadata-Version: 2.4
Name: llm-proxier
Version: 0.3.0
Summary: A lightweight LLM proxy with logging and admin dashboard
Project-URL: Repository, https://github.com/WqyJh/llm-proxier.git
License-File: LICENSE
Requires-Python: >=3.12
Requires-Dist: aiosqlite>=0.19.0
Requires-Dist: alembic>=1.13.1
Requires-Dist: fastapi>=0.109.0
Requires-Dist: greenlet>=3.2.4
Requires-Dist: httpx>=0.26.0
Requires-Dist: pydantic-settings>=2.1.0
Requires-Dist: sqlalchemy>=2.0.25
Requires-Dist: uvicorn[standard]>=0.27.0
